TidySeaborn/GetSeabornData.py
TidySeaborn/MatplotlibDiy.py
TidySeaborn/README.md
TidySeaborn/TidySeabornFlexible.py
TidySeaborn/__init__.py
TidySeaborn/fonts/FZSTK.TTF
TidySeaborn/fonts/FZYTK.TTF
TidySeaborn/fonts/SIMLI.TTF
TidySeaborn/fonts/SIMYOU.TTF
TidySeaborn/fonts/STCAIYUN.TTF
TidySeaborn/fonts/STFANGSO.TTF
TidySeaborn/fonts/STHUPO.TTF
TidySeaborn/fonts/STKAITI.TTF
TidySeaborn/fonts/STLITI.TTF
TidySeaborn/fonts/STSONG.TTF
TidySeaborn/fonts/STXIHEI.TTF
TidySeaborn/fonts/STXINGKA.TTF
TidySeaborn/fonts/STXINWEI.TTF
TidySeaborn/fonts/STZHONGS.TTF
TidySeaborn/fonts/arial.ttf
TidySeaborn/fonts/msyhl.ttc
TidySeaborn/fonts/simfang.ttf
TidySeaborn/fonts/simhei.ttf
TidySeaborn/fonts/simkai.ttf
TidySeaborn/fonts/simsun.ttc
TidySeaborn/fonts/times.ttf
TidySeaborn/test/Starttest.py
TidySeaborn/test/renumberid.py
TidySeaborn/test/testGetSeabornData.txt
TidySeaborn/test/testMatplotlibDiy.txt
TidySeaborn/test/testTidySeabornFlexible.txt
TidySeaborn/test/image/函数拟合图.png
TidySeaborn/test/image/分类变量柱状图.png
TidySeaborn/test/image/分面图.png
TidySeaborn/test/image/小提琴图.png
TidySeaborn/test/image/抖动图.png
TidySeaborn/test/image/散点图.png
TidySeaborn/test/image/柱状图.png
TidySeaborn/test/image/核密度估计图.png
TidySeaborn/test/image/残差图.png
TidySeaborn/test/image/点状误差图.png
TidySeaborn/test/image/热图.png
TidySeaborn/test/image/直方图.png
TidySeaborn/test/image/矩阵散点图.png
TidySeaborn/test/image/箱线图.png
TidySeaborn/test/image/线图.png
TidySeaborn/test/image/经验分布函数图.png
TidySeaborn/test/image/联合分布图.png
tidyseaborn-0.0.4.dist-info/METADATA
tidyseaborn-0.0.4.dist-info/WHEEL
tidyseaborn-0.0.4.dist-info/licenses/LICENSE
tidyseaborn-0.0.4.dist-info/RECORD
