Metadata-Version: 2.1
Name: TidySeaborn
Version: 0.0.4
Summary: 使用Seaborn库绘图的简洁程序库，一行代码搞定所有统计图！
Project-URL: Homepage, https://github.com/LiuAndy-art/TidySeaborn
Project-URL: Documentation, https://github.com/LiuAndy-art/TidySeaborn
Project-URL: Repository, https://github.com/LiuAndy-art/TidySeaborn
Author-email: LiuAndy <andylau_dh@163.com>
Maintainer-email: LiuAndy <andylau_dh@163.com>
License: MIT License
License-File: LICENSE
Keywords: Seaborn,函数封装,简介代码,统计绘图
Classifier: License :: OSI Approved :: MIT License
Classifier: Operating System :: OS Independent
Classifier: Programming Language :: Python :: 3
Requires-Python: >=3.8
Requires-Dist: matplotlib
Requires-Dist: numpy
Requires-Dist: openpyxl
Requires-Dist: pandas
Requires-Dist: scipy
Requires-Dist: seaborn
Requires-Dist: statsmodels
Requires-Dist: xlrd
Requires-Dist: xlsxwriter
Requires-Dist: xlwt
